{
  "schemaVersion": 1,
  "id": "emeraldtools",
  "version": "${version}",

  "name": "val8119's Emerald Tools",
  "description": "Adds emerald tools and armor.",
  "authors": ["val8119"],
  "contact": {
    "homepage": "https://github.com/val8119/emerald_tools",
    "sources": ""
  },

  "license": "CC0-1.0",
  "icon": "assets/emeraldtools/icon.png",

  "environment": "*",
  "entrypoints": {
    "main": ["val8119.emerald.tools.EmeraldTools"]
  },
  "mixins": ["emeraldtools.mixins.json"],

  "depends": {
    "fabricloader": ">=0.7.4",
    "fabric": "*",
    "minecraft": "1.16.x"
  },
  "suggests": {
    "another-mod": "*"
  }
}
